AUTHORS.rst
CONTRIBUTING.rst
HISTORY.rst
LICENSE
MANIFEST.in
README.rst
setup.cfg
setup.py
cid/__init__.py
cid/cid.py
docs/Makefile
docs/api_reference.rst
docs/authors.rst
docs/conf.py
docs/contributing.rst
docs/history.rst
docs/index.rst
docs/make.bat
docs/usage.rst
planetmint_py_cid.egg-info/PKG-INFO
planetmint_py_cid.egg-info/SOURCES.txt
planetmint_py_cid.egg-info/dependency_links.txt
planetmint_py_cid.egg-info/not-zip-safe
planetmint_py_cid.egg-info/requires.txt
planetmint_py_cid.egg-info/top_level.txt
tests/__init__.py
tests/test_cid.py