Metadata-Version: 2.1
Name: planetmint-py-cid
Version: 0.4.1
Summary: Self-describing content-addressed identifiers for distributed systems
Home-page: https://github.com/planetmint/py-cid
Author: Dhruv Baldawa
Author-email: mail@planetmint.io
License: MIT license
Keywords: cid
Classifier: Development Status :: 2 - Pre-Alpha
Classifier: Intended Audience :: Developers
Classifier: License :: OSI Approved :: MIT License
Classifier: Natural Language :: English
Classifier: Programming Language :: Python :: 3
Classifier: Programming Language :: Python :: 3.6
Classifier: Programming Language :: Python :: 3.7
Classifier: Programming Language :: Python :: 3.8
Classifier: Programming Language :: Python :: 3.9
Requires-Python: >=3.6
License-File: LICENSE
License-File: AUTHORS.rst
